tab_aaron_alphabet/__init__.py
tab_aaron_alphabet/__main__.py
tab_aaron_alphabet-0.0.3.dist-info/LICENSE
tab_aaron_alphabet-0.0.3.dist-info/METADATA
tab_aaron_alphabet-0.0.3.dist-info/WHEEL
tab_aaron_alphabet-0.0.3.dist-info/top_level.txt
tab_aaron_alphabet-0.0.3.dist-info/RECORD
