Metadata-Version: 2.1
Name: tab-aaron-alphabet
Version: 0.0.3
Summary: Convert tab to 4 spaces. 
Author-email: Aaron Alphabet <aaron.alphabet@posteo.org>
License: Copyright © 2023 Aaron Alphabet
Classifier: License :: OSI Approved :: MIT License
Classifier: Programming Language :: Python
Classifier: Programming Language :: Python :: 3
Requires-Python: >=3.11
License-File: LICENSE
Requires-Dist: os-aaron-alphabet (>=0.0.3)
